affinidi_tdk_login_configuration_client/__init__.py
affinidi_tdk_login_configuration_client/api/__init__.py
affinidi_tdk_login_configuration_client/api/allow_list_api.py
affinidi_tdk_login_configuration_client/api/configuration_api.py
affinidi_tdk_login_configuration_client/api/deny_list_api.py
affinidi_tdk_login_configuration_client/api/group_api.py
affinidi_tdk_login_configuration_client/api/idp_api.py
affinidi_tdk_login_configuration_client/api_client.py
affinidi_tdk_login_configuration_client/api_response.py
affinidi_tdk_login_configuration_client/configuration.py
affinidi_tdk_login_configuration_client/exceptions.py
affinidi_tdk_login_configuration_client/models/__init__.py
affinidi_tdk_login_configuration_client/models/action_forbidden_error.py
affinidi_tdk_login_configuration_client/models/add_user_to_group_input.py
affinidi_tdk_login_configuration_client/models/authorization_request_dcql.py
affinidi_tdk_login_configuration_client/models/authorization_request_pex.py
affinidi_tdk_login_configuration_client/models/blocked_users.py
affinidi_tdk_login_configuration_client/models/blocked_users_input.py
affinidi_tdk_login_configuration_client/models/cors_login_session_accept_response_ok.py
affinidi_tdk_login_configuration_client/models/cors_login_session_for_idp_ok.py
affinidi_tdk_login_configuration_client/models/cors_login_session_reject_response_ok.py
affinidi_tdk_login_configuration_client/models/create_group_input.py
affinidi_tdk_login_configuration_client/models/create_hydra_network_error.py
affinidi_tdk_login_configuration_client/models/create_login_configuration_input.py
affinidi_tdk_login_configuration_client/models/create_login_configuration_output.py
affinidi_tdk_login_configuration_client/models/create_login_configuration_output_auth.py
affinidi_tdk_login_configuration_client/models/create_login_configurations400_response.py
affinidi_tdk_login_configuration_client/models/create_project_network_error.py
affinidi_tdk_login_configuration_client-1.59.0.dist-info/METADATA
affinidi_tdk_login_configuration_client-1.59.0.dist-info/WHEEL
affinidi_tdk_login_configuration_client-1.59.0.dist-info/RECORD
